iperform/__init__.py
iperform/core.py
iperform/formatting.py
iperform/metrics.py
iperform/modeling.py
iperform/plotting.py
iperform/prepocessing.py
iperform/utils.py
iperform-0.3.0.dist-info/licenses/LICENSE
iperform-0.3.0.dist-info/METADATA
iperform-0.3.0.dist-info/WHEEL
iperform-0.3.0.dist-info/top_level.txt
iperform-0.3.0.dist-info/RECORD
