Metadata-Version: 2.4
Name: iperform
Version: 0.3.0
Summary: Monitor, Decide, act - with precise KPIs, smart alerts, and reliable forecasts. In a few lines code.
Author-email: ILUNGA BUABUA Patrick <buabua@internet.ru>
License: MIT
Project-URL: Homepage, https://github.com/ipatriqIP/iperform
Requires-Python: <3.11,>=3.10
License-File: LICENSE
Requires-Dist: numpy<2.0,>=1.21
Requires-Dist: scipy>=1.13
Requires-Dist: pandas>=1.3
Requires-Dist: matplotlib>=3.4
Requires-Dist: seaborn>=0.11
Requires-Dist: geopandas>=1.0.1
Requires-Dist: lightgbm>=4.0
Requires-Dist: folium>=0.14.0
Provides-Extra: dev
Requires-Dist: pytest; extra == "dev"
Requires-Dist: black; extra == "dev"
Requires-Dist: flake8; extra == "dev"
Requires-Dist: ipython; extra == "dev"
Provides-Extra: forecasting
Requires-Dist: statsmodels<0.15,>=0.14; extra == "forecasting"
Requires-Dist: pmdarima>=2.0; extra == "forecasting"
Requires-Dist: torch<2.0,>=1.7; extra == "forecasting"
Requires-Dist: pytorch-lightning==1.9.4; extra == "forecasting"
Requires-Dist: pytorch-forecasting==0.10.1; extra == "forecasting"
Requires-Dist: tensorboard; extra == "forecasting"
Requires-Dist: scikit-learn>=1.0; extra == "forecasting"
Requires-Dist: xgboost>=2.0; extra == "forecasting"
Requires-Dist: tensorflow>=2.15; extra == "forecasting"
Dynamic: license-file
